bin/__init__.py
bin/infer.py
bin/make_mixture.py
bin/make_mixture_nooverlap.py
bin/make_rttm.py
bin/model_averaging.py
bin/random_mixture.py
bin/random_mixture_nooverlap.py
bin/rttm_stats.py
bin/train.py
bin/visualize_attention.py
bin/yaml2bash.py
chainer_backend/__init__.py
chainer_backend/diarization_dataset.py
chainer_backend/encoder_decoder_attractor.py
chainer_backend/infer.py
chainer_backend/models.py
chainer_backend/train.py
chainer_backend/transformer.py
chainer_backend/updater.py
chainer_backend/utils.py
data/__init__.py
data/mixture.py.py
models/__init__.py
models/blstm.py
models/transformer.py
utils/__init__.py
utils/feature.py
utils/kaldi_data.py
utils/rttm.py
eend-0.1.0.dist-info/METADATA
eend-0.1.0.dist-info/WHEEL
eend-0.1.0.dist-info/entry_points.txt
eend-0.1.0.dist-info/top_level.txt
eend-0.1.0.dist-info/RECORD
